iexec_doracle/__init__.py
iexec_doracle-0.0.1.dist-info/LICENSE
iexec_doracle-0.0.1.dist-info/METADATA
iexec_doracle-0.0.1.dist-info/WHEEL
iexec_doracle-0.0.1.dist-info/top_level.txt
iexec_doracle-0.0.1.dist-info/RECORD
