Metadata-Version: 2.1
Name: iexec-doracle
Version: 0.0.1
Summary: Tooling for build iExec doracles in python
Home-page: https://github.com/iExecBlockchainComputing/iexec-doracle-pip
Author: iExec
Author-email: dev@iex.ec
License: UNKNOWN
Platform: UNKNOWN
Classifier: Programming Language :: Python :: 3
Classifier: License :: OSI Approved :: Apache Software License
Classifier: Operating System :: OS Independent
Requires-Python: >=3.6
